wms_library/__init__.py
wms_library/date_util.py
wms_library/util_validate.py
wms_library/calculators/__init__.py
wms_library/calculators/wms_calculator.py
wms_library/exceptions/__init__.py
wms_library/exceptions/wms_exception.py
wms_library/helpers/__init__.py
wms_library/helpers/data_helper.py
wms_library/helpers/s3_helper.py
x22223673_ewarranty_management-0.0.4.dist-info/LICENSE.txt
x22223673_ewarranty_management-0.0.4.dist-info/METADATA
x22223673_ewarranty_management-0.0.4.dist-info/WHEEL
x22223673_ewarranty_management-0.0.4.dist-info/top_level.txt
x22223673_ewarranty_management-0.0.4.dist-info/RECORD
