Metadata-Version: 2.1
Name: x22223673_ewarranty_management
Version: 0.0.4
Summary: Electronic Warranty Management System Library
Home-page: https://github.com/venky.dbl
Author: Venky.dbl
Author-email: venky.dbl@gmail.com
License: UNKNOWN
Platform: UNKNOWN
Classifier: Programming Language :: Python :: 3
Classifier: License :: OSI Approved :: MIT License
Classifier: Operating System :: OS Independent
Requires-Python: >=3.6
License-File: LICENSE.txt
